RCutter/__init__.py
RCutter/cutter.py
RCutter/utils.py
RCutter-0.0.9.dist-info/LICENSE
RCutter-0.0.9.dist-info/METADATA
RCutter-0.0.9.dist-info/WHEEL
RCutter-0.0.9.dist-info/top_level.txt
RCutter-0.0.9.dist-info/RECORD
